{
    "indexes": [
        {
            "collectionGroup": "members",
            "queryScope": "COLLECTION_GROUP",
            "fields": [
                {
                    "fieldPath": "familyDocId",
                    "order": "ASCENDING"
                },
                {
                    "fieldPath": "fullName",
                    "order": "ASCENDING"
                }
            ]
        },
        {
            "collectionGroup": "members",
            "queryScope": "COLLECTION",
            "fields": [
                {
                    "fieldPath": "familyId",
                    "order": "ASCENDING"
                },
                {
                    "fieldPath": "isActive",
                    "order": "ASCENDING"
                },
                {
                    "fieldPath": "fullName",
                    "order": "ASCENDING"
                }
            ]
        }
    ],
    "fieldOverrides": [
        {
            "collectionGroup": "members",
            "fieldPath": "mid",
            "indexes": [
                {
                    "order": "ASCENDING",
                    "queryScope": "COLLECTION_GROUP"
                },
                {
                    "order": "DESCENDING",
                    "queryScope": "COLLECTION_GROUP"
                }
            ]
        },
        {
            "collectionGroup": "members",
            "fieldPath": "familyDocId",
            "indexes": [
                {
                    "order": "ASCENDING",
                    "queryScope": "COLLECTION_GROUP"
                },
                {
                    "order": "DESCENDING",
                    "queryScope": "COLLECTION_GROUP"
                }
            ]
        }
    ]
}